{
	"configurations" : 
	[
		{
			"directories" : 
			[
				{
					"build" : ".",
					"jsonFile" : "directory-.-Debug-f5ebdc15457944623624.json",
					"minimumCMakeVersion" : 
					{
						"string" : "3.25"
					},
					"projectIndex" : 0,
					"source" : ".",
					"targetIndexes" : 
					[
						0
					]
				}
			],
			"name" : "Debug",
			"projects" : 
			[
				{
					"directoryIndexes" : 
					[
						0
					],
					"name" : "Room_Allocation",
					"targetIndexes" : 
					[
						0
					]
				}
			],
			"targets" : 
			[
				{
					"directoryIndex" : 0,
					"id" : "Room_Allocation::@6890427a1f51a3e7e1df",
					"jsonFile" : "target-Room_Allocation-Debug-add932dcc56f56ee0b72.json",
					"name" : "Room_Allocation",
					"projectIndex" : 0
				}
			]
		}
	],
	"kind" : "codemodel",
	"paths" : 
	{
		"build" : "/home/max/All_Projects/Algorithms_and_DS/CSES/Sorting And Searching/Room Allocation/cmake-build-debug",
		"source" : "/home/max/All_Projects/Algorithms_and_DS/CSES/Sorting And Searching/Room Allocation"
	},
	"version" : 
	{
		"major" : 2,
		"minor" : 4
	}
}
